setup.py
sjoh/__init__.py
sjoh/flask.py
sjoh.egg-info/PKG-INFO
sjoh.egg-info/SOURCES.txt
sjoh.egg-info/dependency_links.txt
sjoh.egg-info/requires.txt
sjoh.egg-info/top_level.txt