Metadata-Version: 1.1
Name: sjoh
Version: 2.1.0
Summary: Implementation of the Simple JSON over HTTP protocol.
Home-page: https://github.com/nicolas-van/sjoh.py
Author: Nicolas Vanhoren
Author-email: nicolas.vanhoren@gmail.com
License: MIT
Platform: any
Classifier: Intended Audience :: Developers
Classifier: License :: OSI Approved :: MIT License
Classifier: Operating System :: OS Independent
Classifier: Programming Language :: Python
Classifier: Topic :: Software Development :: Libraries :: Python Modules
